<?xml version="1.0" encoding="UTF-8"?>

<!--
    Copyright (c) 2015 onox

    This program is free software: you can redistribute it and/or modify
    it under the terms of the GNU General Public License as published by
    the Free Software Foundation, either version 3 of the License, or
    (at your option) any later version.

    This program is distributed in the hope that it will be useful,
    but WITHOUT ANY WARRANTY; without even the implied warranty of
    MERCHANTABILITY or FITNESS FOR A PARTICULAR PURPOSE.  See the
    GNU General Public License for more details.

    You should have received a copy of the GNU General Public License
    along with this program.  If not, see <http://www.gnu.org/licenses/>.
-->

<PropertyList>

    <name>type</name>
    <layout>vbox</layout>
    <width>250</width>
    <resizable>false</resizable>

    <group>
        <layout>hbox</layout>

        <empty><stretch>true</stretch></empty>
        <text>
            <label>Type</label>
        </text>
        <empty><stretch>true</stretch></empty>

        <button>
            <legend/>
            <keynum>27</keynum>
            <pref-width>16</pref-width>
            <pref-height>16</pref-height>
            <border>2</border>
            <binding>
                <command>dialog-close</command>
            </binding>
        </button>
    </group>

    <hrule/>

    <group>
        <layout>vbox</layout>
        <default-padding>6</default-padding>

        <empty><stretch>true</stretch></empty>

        <button>
            <legend>Depot</legend>
            <binding>
                <command>property-assign</command>
                <property>sim/multiplay/generic/int[17]</property>
                <value>0</value>
            </binding>
        </button>
        <button>
            <legend>Shelter</legend>
            <binding>
                <command>property-assign</command>
                <property>sim/multiplay/generic/int[17]</property>
                <value>1</value>
            </binding>
        </button>
        <button>
            <legend>Fuel</legend>
            <binding>
                <command>property-assign</command>
                <property>sim/multiplay/generic/int[17]</property>
                <value>2</value>
            </binding>
        </button>
        <button>
            <legend>Small Hangar</legend>
            <binding>
                <command>property-assign</command>
                <property>sim/multiplay/generic/int[17]</property>
                <value>3</value>
            </binding>
        </button>
        <button>
            <legend>Hangar</legend>
            <binding>
                <command>property-assign</command>
                <property>sim/multiplay/generic/int[17]</property>
                <value>4</value>
            </binding>
        </button>
        <button>
            <legend>Factory</legend>
            <binding>
                <command>property-assign</command>
                <property>sim/multiplay/generic/int[17]</property>
                <value>5</value>
            </binding>
        </button>
        <button>
            <legend>Plex</legend>
            <binding>
                <command>property-assign</command>
                <property>sim/multiplay/generic/int[17]</property>
                <value>6</value>
            </binding>
        </button>
        <button>
            <legend>Container</legend>
            <binding>
                <command>property-assign</command>
                <property>sim/multiplay/generic/int[17]</property>
                <value>7</value>
            </binding>
        </button>

        <button>
            <legend>Hill Target</legend>
            <binding>
                <command>property-assign</command>
                <property>sim/multiplay/generic/int[17]</property>
                <value>8</value>
            </binding>
        </button>

        <button>
            <legend>Cliff Target</legend>
            <binding>
                <command>property-assign</command>
                <property>sim/multiplay/generic/int[17]</property>
                <value>9</value>
            </binding>
        </button>

    </group>

</PropertyList>
